{
    "indexes": [
        {
            "collectionGroup": "mesecni_putnici",
            "queryScope": "COLLECTION",
            "fields": [
                {
                    "fieldPath": "vozac_id",
                    "order": "ASCENDING"
                },
                {
                    "fieldPath": "created_at",
                    "order": "DESCENDING"
                }
            ]
        },
        {
            "collectionGroup": "mesecni_putnici",
            "queryScope": "COLLECTION",
            "fields": [
                {
                    "fieldPath": "vozac_id",
                    "order": "ASCENDING"
                },
                {
                    "fieldPath": "aktivan",
                    "order": "ASCENDING"
                },
                {
                    "fieldPath": "created_at",
                    "order": "DESCENDING"
                }
            ]
        },
        {
            "collectionGroup": "mesecni_putnici",
            "queryScope": "COLLECTION",
            "fields": [
                {
                    "fieldPath": "aktivan",
                    "order": "ASCENDING"
                },
                {
                    "fieldPath": "putnik_ime",
                    "order": "ASCENDING"
                }
            ]
        },
        {
            "collectionGroup": "dnevni_putnici",
            "queryScope": "COLLECTION",
            "fields": [
                {
                    "fieldPath": "vozac_id",
                    "order": "ASCENDING"
                },
                {
                    "fieldPath": "datum_putovanja",
                    "order": "DESCENDING"
                }
            ]
        },
        {
            "collectionGroup": "gps_lokacije",
            "queryScope": "COLLECTION",
            "fields": [
                {
                    "fieldPath": "vozac_id",
                    "order": "ASCENDING"
                },
                {
                    "fieldPath": "vreme",
                    "order": "DESCENDING"
                }
            ]
        },
        {
            "collectionGroup": "gps_lokacije",
            "queryScope": "COLLECTION",
            "fields": [
                {
                    "fieldPath": "vozac_id",
                    "order": "ASCENDING"
                },
                {
                    "fieldPath": "aktivan",
                    "order": "ASCENDING"
                },
                {
                    "fieldPath": "vreme",
                    "order": "DESCENDING"
                }
            ]
        },
        {
            "collectionGroup": "gps_lokacije",
            "queryScope": "COLLECTION",
            "fields": [
                {
                    "fieldPath": "vozac_id",
                    "order": "ASCENDING"
                },
                {
                    "fieldPath": "vreme",
                    "order": "ASCENDING"
                },
                {
                    "fieldPath": "aktivan",
                    "order": "ASCENDING"
                }
            ]
        },
        {
            "collectionGroup": "putovanja_istorija",
            "queryScope": "COLLECTION",
            "fields": [
                {
                    "fieldPath": "vozac_id",
                    "order": "ASCENDING"
                },
                {
                    "fieldPath": "datum_putovanja",
                    "order": "DESCENDING"
                }
            ]
        },
        {
            "collectionGroup": "putovanja_istorija",
            "queryScope": "COLLECTION",
            "fields": [
                {
                    "fieldPath": "vozac_id",
                    "order": "ASCENDING"
                },
                {
                    "fieldPath": "status",
                    "order": "ASCENDING"
                },
                {
                    "fieldPath": "datum_putovanja",
                    "order": "DESCENDING"
                }
            ]
        },
        {
            "collectionGroup": "putovanja_istorija",
            "queryScope": "COLLECTION",
            "fields": [
                {
                    "fieldPath": "mesecni_putnik_id",
                    "order": "ASCENDING"
                },
                {
                    "fieldPath": "datum_putovanja",
                    "order": "DESCENDING"
                }
            ]
        },
        {
            "collectionGroup": "putovanja_istorija",
            "queryScope": "COLLECTION",
            "fields": [
                {
                    "fieldPath": "tip_putnika",
                    "order": "ASCENDING"
                },
                {
                    "fieldPath": "datum_putovanja",
                    "order": "DESCENDING"
                }
            ]
        },
        {
            "collectionGroup": "vozila",
            "queryScope": "COLLECTION",
            "fields": [
                {
                    "fieldPath": "vlasnik_id",
                    "order": "ASCENDING"
                },
                {
                    "fieldPath": "aktivan",
                    "order": "ASCENDING"
                }
            ]
        },
        {
            "collectionGroup": "rute",
            "queryScope": "COLLECTION",
            "fields": [
                {
                    "fieldPath": "vozac_id",
                    "order": "ASCENDING"
                },
                {
                    "fieldPath": "created_at",
                    "order": "DESCENDING"
                }
            ]
        },
        {
            "collectionGroup": "notifications",
            "queryScope": "COLLECTION",
            "fields": [
                {
                    "fieldPath": "user_id",
                    "order": "ASCENDING"
                },
                {
                    "fieldPath": "procitano",
                    "order": "ASCENDING"
                },
                {
                    "fieldPath": "timestamp",
                    "order": "DESCENDING"
                }
            ]
        },
        {
            "collectionGroup": "mesecni_putnici",
            "queryScope": "COLLECTION",
            "fields": [
                {
                    "fieldPath": "search_terms",
                    "order": "ASCENDING"
                },
                {
                    "fieldPath": "aktivan",
                    "order": "ASCENDING"
                }
            ]
        },
        {
            "collectionGroup": "dnevni_putnici",
            "queryScope": "COLLECTION",
            "fields": [
                {
                    "fieldPath": "datum_polaska",
                    "order": "ASCENDING"
                },
                {
                    "fieldPath": "vozac_id",
                    "order": "ASCENDING"
                }
            ]
        }
    ],
    "fieldOverrides": [
        {
            "collectionGroup": "mesecni_putnici",
            "fieldPath": "adrese",
            "indexes": [
                {
                    "queryScope": "COLLECTION",
                    "arrayConfig": "CONTAINS"
                }
            ]
        },
        {
            "collectionGroup": "vozaci",
            "fieldPath": "rute_ids",
            "indexes": [
                {
                    "queryScope": "COLLECTION",
                    "arrayConfig": "CONTAINS"
                }
            ]
        },
        {
            "collectionGroup": "mesecni_putnici",
            "fieldPath": "search_terms",
            "indexes": [
                {
                    "queryScope": "COLLECTION",
                    "arrayConfig": "CONTAINS"
                }
            ]
        },
        {
            "collectionGroup": "putovanja_istorija",
            "fieldPath": "search_terms",
            "indexes": [
                {
                    "queryScope": "COLLECTION",
                    "arrayConfig": "CONTAINS"
                }
            ]
        }
    ]
}